LICENSE
MANIFEST.in
README.markdown
setup.cfg
setup.py
bin/mm-bolus.py
bin/mm-decode-history-page.py
bin/mm-latest.py
bin/mm-press-key.py
bin/mm-pretty-csv
bin/mm-send-comm.py
bin/mm-set-rtc.py
bin/mm-set-suspend.py
bin/mm-temp-basals.py
decocare/__init__.py
decocare/commands.py
decocare/download.py
decocare/errors.py
decocare/fuser.py
decocare/history.py
decocare/lib.py
decocare/link.py
decocare/scan.py
decocare/session.py
decocare/stick.py
decocare.egg-info/PKG-INFO
decocare.egg-info/SOURCES.txt
decocare.egg-info/dependency_links.txt
decocare.egg-info/not-zip-safe
decocare.egg-info/requires.txt
decocare.egg-info/top_level.txt
decocare/cgm/__init__.py
decocare/etc/80-medtronic-carelink.rules
decocare/helpers/__init__.py
decocare/helpers/cli.py
decocare/helpers/messages.py
decocare/models/__init__.py
decocare/records/__init__.py
decocare/records/base.py
decocare/records/bolus.py
decocare/records/tests.py
decocare/records/times.py