Metadata-Version: 1.1
Name: decocare
Version: 0.0.31
Summary: Audit, inspect, and command MM insulin pumps.
Home-page: https://github.com/openaps/decocare
Author: Ben West
Author-email: bewest+insulaudit@gmail.com
License: UNKNOWN
Platform: UNKNOWN
Classifier: Development Status :: 3 - Alpha
Classifier: Intended Audience :: Developers
Classifier: Intended Audience :: Science/Research
Classifier: Programming Language :: Python
Classifier: Topic :: Scientific/Engineering
Classifier: Topic :: Software Development :: Libraries
